README.txt
setup.py
txboxdotnet/__init__.py
txboxdotnet/api_v2.py
txboxdotnet.egg-info/PKG-INFO
txboxdotnet.egg-info/SOURCES.txt
txboxdotnet.egg-info/dependency_links.txt
txboxdotnet.egg-info/requires.txt
txboxdotnet.egg-info/top_level.txt